bmo/__init__.py
bmo/cicd.py
bmo/common.py
bmo/devops.py
bmo/doctor.py
bmo/helpers/notion.py
bmo/info.py
bmo/install.py
bmo/main.py
bmo/monitor_infra.py
bmo/network.py
bmo/org.py
bmo/run.py
bmo/scripts/check_certificate.xsh
bmo/subcom/__init__.py
bmo/system.py
bmo/version.py
bmo-0.4.4.dist-info/entry_points.txt
bmo-0.4.4.dist-info/LICENSE
bmo-0.4.4.dist-info/WHEEL
bmo-0.4.4.dist-info/METADATA
bmo-0.4.4.dist-info/RECORD
