Metadata-Version: 2.1
Name: bmo
Version: 0.4.4
Summary: BMO automates stuff at SubCom
License: GPLv3
Author: Dilawar Singh
Author-email: dilawar@subcom.tech
Requires-Python: >=3.7.3,<4
Classifier: License :: Other/Proprietary License
Classifier: Programming Language :: Python :: 3
Classifier: Programming Language :: Python :: 3.8
Classifier: Programming Language :: Python :: 3.9
Classifier: Programming Language :: Python :: 3.10
Classifier: Programming Language :: Python :: 3.11
Requires-Dist: Envelopes (>=0.4,<0.5)
Requires-Dist: PyYAML (>=6.0,<7.0)
Requires-Dist: html2text (>=2020.1.16,<2021.0.0)
Requires-Dist: importlib-resources (>=5.8.0,<6.0.0); python_version == "3.7"
Requires-Dist: msgpack (>=1.0.4,<2.0.0)
Requires-Dist: pydig (>=0.4.0,<0.5.0)
Requires-Dist: python-dateutil (>=2.8.2,<3.0.0)
Requires-Dist: python3-nmap (>=1.5.4,<2.0.0)
Requires-Dist: requests[security] (>=2.28.0,<3.0.0)
Requires-Dist: rich (>=12.5.1,<13.0.0)
Requires-Dist: sentry-sdk (>=1.6.0,<2.0.0)
Requires-Dist: speedtest-cli (>=2.1.3,<3.0.0)
Requires-Dist: toml (>=0.10.2,<0.11.0)
Requires-Dist: typed-ast (>=1.5.4,<2.0.0)
Requires-Dist: typer (>=0.4.1,<0.5.0)
